easyCore/REDIRECT.py
easyCore/__init__.py
easyCore/Datasets/__init__.py
easyCore/Datasets/xarray.py
easyCore/Fitting/Constraints.py
easyCore/Fitting/DFO_LS.py
easyCore/Fitting/Fitting.py
easyCore/Fitting/__init__.py
easyCore/Fitting/bumps.py
easyCore/Fitting/fitting_template.py
easyCore/Fitting/lmfit.py
easyCore/Objects/Borg.py
easyCore/Objects/Graph.py
easyCore/Objects/Groups.py
easyCore/Objects/Inferface.py
easyCore/Objects/ObjectClasses.py
easyCore/Objects/Variable.py
easyCore/Objects/__init__.py
easyCore/Objects/core.py
easyCore/Objects/virtual.py
easyCore/Utils/Exceptions.py
easyCore/Utils/Logging.py
easyCore/Utils/UndoRedo.py
easyCore/Utils/__init__.py
easyCore/Utils/classTools.py
easyCore/Utils/classUtils.py
easyCore/Utils/decorators.py
easyCore/Utils/string.py
easyCore/Utils/typing.py
easyCore/Utils/Hugger/Hugger.py
easyCore/Utils/Hugger/Property.py
easyCore/Utils/Hugger/__init__.py
easyCore/Utils/io/__init__.py
easyCore/Utils/io/dict.py
easyCore/Utils/io/json.py
easyCore/Utils/io/star.py
easyCore/Utils/io/template.py
easyCore/Utils/io/xml.py
easyCore/models/__init__.py
easyCore/models/polynomial.py
easysciencecore-0.5.1.dist-info/METADATA
easysciencecore-0.5.1.dist-info/WHEEL
easysciencecore-0.5.1.dist-info/licenses/LICENSE
easysciencecore-0.5.1.dist-info/RECORD
