Metadata-Version: 2.1
Name: easysciencecore
Version: 0.5.1
Summary: Generic logic for easyScience libraries
Project-URL: homepage, https://github.com/easyScience/easyCore
Project-URL: documentation, https://github.com/easyScience/easyCore
Author: Simon Ward
Author-email: Andreas Pedersen <andreas.pedersen@ess.eu>
Maintainer-email: Andreas Pedersen <andreas.pedersen@ess.eu>
License-Expression: BSD-3-Clause
License-File: LICENSE
Classifier: Development Status :: 3 - Alpha
Classifier: License :: OSI Approved :: BSD License
Classifier: Operating System :: OS Independent
Classifier: Programming Language :: Python :: 3
Classifier: Topic :: Scientific/Engineering
Requires-Python: <3.12,>=3.9
Requires-Dist: asteval
Requires-Dist: bumps
Requires-Dist: dfo-ls
Requires-Dist: lmfit
Requires-Dist: numpy
Requires-Dist: pint
Requires-Dist: uncertainties
Requires-Dist: xarray
Provides-Extra: dev
Requires-Dist: build; extra == 'dev'
Requires-Dist: codecov; extra == 'dev'
Requires-Dist: flake8; extra == 'dev'
Requires-Dist: matplotlib; extra == 'dev'
Requires-Dist: pytest; extra == 'dev'
Requires-Dist: pytest-cov; extra == 'dev'
Requires-Dist: ruff; extra == 'dev'
Requires-Dist: tox-gh-actions; extra == 'dev'
Provides-Extra: docs
Requires-Dist: doc8; extra == 'docs'
Requires-Dist: readme-renderer; extra == 'docs'
Requires-Dist: sphinx; extra == 'docs'
Requires-Dist: sphinx-autodoc-typehints; extra == 'docs'
Requires-Dist: sphinx-gallery; extra == 'docs'
Requires-Dist: sphinx-rtd-theme; extra == 'docs'
Requires-Dist: toml; extra == 'docs'
